{
  "id": "homage-machine-memory-anadol",
  "artistId": "refik-anadol",
  "movementId": null,
  "title": "Homage: Machine Memory",
  "year": null,
  "imageUrl": "",
  "source": "ai-generated",
  "licenseType": "Original AI-generated homage",
  "width": 1536,
  "height": 1536,
  "description": "An original AI-generated homage in the artist's spirit — their actual works remain under copyright.",
  "generationPrompt": "ai data sculpture, billowing volumetric clouds of colored particles morphing between architecture and dream, deep blacks with neon chroma, gallery-scale digital canvas, sublime computational abstraction"
}
