{
  "id": "homage-figure-in-flux-kooning",
  "artistId": "willem-de-kooning",
  "movementId": null,
  "title": "Homage: Figure in Flux",
  "year": null,
  "imageUrl": "",
  "source": "ai-generated",
  "licenseType": "Original AI-generated homage",
  "width": 1536,
  "height": 1536,
  "description": "An original AI-generated homage in the artist's spirit — their actual works remain under copyright.",
  "generationPrompt": "abstract expressionist figure painting, frenzied pink and flesh-toned female figure dissolving into slashing brushstrokes, toothy grin, charcoal lines through wet oil paint, violent energetic gesture, 1950s New York school"
}
